tf_contextual_prediction_with_expert_advice/__init__.py
tf_contextual_prediction_with_expert_advice/rrm.py
tf_contextual_prediction_with_expert_advice-0.0.1.dist-info/METADATA
tf_contextual_prediction_with_expert_advice-0.0.1.dist-info/RECORD
tf_contextual_prediction_with_expert_advice-0.0.1.dist-info/WHEEL
tf_contextual_prediction_with_expert_advice-0.0.1.dist-info/top_level.txt
