Metadata-Version: 2.1
Name: tf-contextual-prediction-with-expert-advice
Version: 0.0.1
Summary: UNKNOWN
Home-page: UNKNOWN
Author: UNKNOWN
Author-email: UNKNOWN
License: UNKNOWN
Platform: UNKNOWN
Requires-Dist: setuptools (>=20.2.2)
